primebit/README.md
primebit/__init__.py
primebit/colors.py
primebit/primebit.py
primebit-0.2.1.dist-info/METADATA
primebit-0.2.1.dist-info/WHEEL
primebit-0.2.1.dist-info/RECORD
